{
  "paths": {
    "path11": {
      "type": "path",
      "points": [
        {
          "x": -0.541495829500001,
          "y": 0.044368009536419395
        },
        {
          "x": -0.21998262950000114,
          "y": 0.044368009536419395
        }
      ],
      "color": "primary",
      "fill": false
    },
    "path12": {
      "type": "path",
      "points": [
        {
          "x": 0.14450697049999905,
          "y": 0.052237309536419474
        },
        {
          "x": 0.46379767049999976,
          "y": 0.052237309536419474
        }
      ],
      "color": "primary",
      "fill": false
    },
    "path12-6": {
      "type": "path",
      "points": [
        {
          "x": 0.13965347050000032,
          "y": -0.14937819046358025
        },
        {
          "x": 0.13854747050000027,
          "y": 0.2538388095364199
        }
      ],
      "color": "primary",
      "fill": false
    },
    "path11-0-9": {
      "type": "path",
      "points": [
        {
          "x": -0.222000900000909,
          "y": 0.250000900000
        },
        {
          "x": -0.222000900000909,
          "y": -0.1600000009000
        },
        {
          "x": 0.1370000090000,
          "y": 0.0540000900000
        },
        {
          "x": -0.222000900000909,
          "y": 0.25000009000
        }
      ],
      "color": "primary",
      "fill": true
    }
  },
  "texts": {
    "top1": {
      "type": "text",
      "text": "{REF}",
      "x": -0.08906882950000083,
      "y": 0.38011220953641867
    },
    "bottom1": {
      "type": "text",
      "text": "{VAL}",
      "x": -0.0685314901614209,
      "y": -0.38011220953641844
    },
    "right1": {
      "type": "text",
      "text": "",
      "x": 0.5884896704999998,
      "y": -0.3288545904635811
    }
  },
  "refblocks": {
    "left1": {
      "x": -0.5603312294999999,
      "y": 0.04351520953641885
    },
    "right1": {
      "x": 0.47524967049999955,
      "y": 0.05238090953641872
    }
  },
  "bounds": {
    "minX": -0.5884896704999999,
    "maxX": 0.5884896704999998,
    "minY": -0.38011220953641844,
    "maxY": 0.38011220953641867,
    "width": 1.1769793409999996,
    "height": 0.7602244190728371,
    "centerX": -5.551115123125783e-17,
    "centerY": 1.1102230246251565e-16
  },
  "circles": {}
}